odoo/addons/l10n_es_payment_order_confirming_sabadell/README.rst
odoo/addons/l10n_es_payment_order_confirming_sabadell/__init__.py
odoo/addons/l10n_es_payment_order_confirming_sabadell/__manifest__.py
odoo/addons/l10n_es_payment_order_confirming_sabadell/data/account_payment_method.xml
odoo/addons/l10n_es_payment_order_confirming_sabadell/i18n/ca.po
odoo/addons/l10n_es_payment_order_confirming_sabadell/i18n/es.po
odoo/addons/l10n_es_payment_order_confirming_sabadell/i18n/l10n_es_payment_order_confirming_sabadell.pot
odoo/addons/l10n_es_payment_order_confirming_sabadell/models/__init__.py
odoo/addons/l10n_es_payment_order_confirming_sabadell/models/account_payment_mode.py
odoo/addons/l10n_es_payment_order_confirming_sabadell/models/account_payment_order.py
odoo/addons/l10n_es_payment_order_confirming_sabadell/models/confirming_sabadell.py
odoo/addons/l10n_es_payment_order_confirming_sabadell/readme/CONFIGURE.rst
odoo/addons/l10n_es_payment_order_confirming_sabadell/readme/CONTRIBUTORS.rst
odoo/addons/l10n_es_payment_order_confirming_sabadell/readme/DESCRIPTION.rst
odoo/addons/l10n_es_payment_order_confirming_sabadell/readme/USAGE.rst
odoo/addons/l10n_es_payment_order_confirming_sabadell/static/description/icon.png
odoo/addons/l10n_es_payment_order_confirming_sabadell/static/description/index.html
odoo/addons/l10n_es_payment_order_confirming_sabadell/tests/__init__.py
odoo/addons/l10n_es_payment_order_confirming_sabadell/tests/test_payment_order_confirming_sabadell.py
odoo/addons/l10n_es_payment_order_confirming_sabadell/views/account_payment_mode_view.xml
odoo14_addon_l10n_es_payment_order_confirming_sabadell-14.0.1.0.4.dist-info/METADATA
odoo14_addon_l10n_es_payment_order_confirming_sabadell-14.0.1.0.4.dist-info/WHEEL
odoo14_addon_l10n_es_payment_order_confirming_sabadell-14.0.1.0.4.dist-info/top_level.txt
odoo14_addon_l10n_es_payment_order_confirming_sabadell-14.0.1.0.4.dist-info/RECORD
