Metadata-Version: 2.1
Name: odoo14-addon-l10n-es-payment-order-confirming-sabadell
Version: 14.0.1.0.4
Summary: Exportación de fichero bancario Confirming para Banco Sabadell
Home-page: https://github.com/OCA/l10n-spain
Author: Soluntec, Odoo Community Association (OCA), Tecnativa
Author-email: support@odoo-community.org
License: AGPL-3
Platform: UNKNOWN
Classifier: Programming Language :: Python
Classifier: Framework :: Odoo
Classifier: Framework :: Odoo :: 14.0
Classifier: License :: OSI Approved :: GNU Affero General Public License v3
Requires-Python: >=3.6
Requires-Dist: odoo14-addon-account-payment-order
Requires-Dist: odoo <14.1dev,>=14.0a
